{
  "type": "FeatureCollection",
  "features": [
    {
      "id": 3676,
      "type": "Feature",
      "properties": {
        "id": "IN_ADM2_76128533B10270619600482",
        "name": "South District",
        "cntr_code": "FRI",
        "__source": "detail"
      },
      "geometry": {
        "type": "Polygon",
        "coordinates": [
          [
            [
              88.37188371883718,
              27.526813509135096
            ],
            [
              88.26388263882637,
              27.519870155701554
            ],
            [
              88.27931136454221,
              27.509455125551263
            ],
            [
              88.29988299883001,
              27.495568418684186
            ],
            [
              88.29988299883001,
              27.420927369273684
            ],
            [
              88.33188331883319,
              27.406269178691787
            ],
            [
              88.37188371883718,
              27.387946440464404
            ],
            [
              88.29988299883001,
              27.317355680556844
            ],
            [
              88.26388263882637,
              27.282060300603007
            ],
            [
              88.3358833588336,
              27.193532544325436
            ],
            [
              88.29988299883001,
              27.12757068670686
            ],
            [
              88.4438844388444,
              27.085910566105653
            ],
            [
              88.55188551885522,
              27.150136585365857
            ],
            [
              88.52532787622958,
              27.185991607194758
            ],
            [
              88.51974234028054,
              27.193532544325436
            ],
            [
              88.51588515885157,
              27.198740059400592
            ],
            [
              88.51588515885157,
              27.242136018360185
            ],
            [
              88.4438844388444,
              27.27338110881108
            ],
            [
              88.51588515885157,
              27.330663774637742
            ],
            [
              88.51588515885157,
              27.37926724867249
            ],
            [
              88.40788407884082,
              27.420927369273684
            ],
            [
              88.40788407884082,
              27.469530843308434
            ],
            [
              88.37188371883718,
              27.526813509135096
            ]
          ]
        ]
      }
    },
    {
      "id": 3789,
      "type": "Feature",
      "properties": {
        "id": "IN_ADM2_76128533B23858286755005",
        "name": "Alipurduar",
        "cntr_code": "FRI",
        "__source": "detail"
      },
      "geometry": {
        "type": "MultiPolygon",
        "coordinates": [
          [
            [
              [
                89.88389883898839,
                26.455801242012413
              ],
              [
                89.88389883898839,
                26.462744595445955
              ],
              [
                89.81189811898122,
                26.438442858428587
              ],
              [
                89.84713251387835,
                26.414658179645627
              ],
              [
                89.8478984789848,
                26.41414112141122
              ],
              [
                89.84913987070905,
                26.41557767729401
              ],
              [
                89.88389883898839,
                26.455801242012413
              ]
            ]
          ],
          [
            [
              [
                89.88389883898839,
                26.462744595445955
              ],
              [
                89.88389883898839,
                26.707497803978043
              ],
              [
                89.77589775897758,
                26.702290288902887
              ],
              [
                89.77589775897758,
                26.733535379353796
              ],
              [
                89.739897398974,
                26.716176995769956
              ],
              [
                89.66789667896683,
                26.74221457114571
              ],
              [
                89.63189631896319,
                26.716176995769956
              ],
              [
                89.63189631896319,
                26.72485618756187
              ],
              [
                89.66789667896683,
                26.76478046980469
              ],
              [
                89.55989559895602,
                26.81685562055621
              ],
              [
                89.45189451894521,
                26.808176428764284
              ],
              [
                89.45189451894521,
                26.839421519215193
              ],
              [
                89.38557806630698,
                26.839421519215193
              ],
              [
                89.37989379893799,
                26.839421519215193
              ],
              [
                89.37989379893799,
                26.84358753127532
              ],
              [
                89.37989379893799,
                26.865459094590946
              ],
              [
                89.31410633903292,
                26.835852917513947
              ],
              [
                89.27189271892718,
                26.81685562055621
              ],
              [
                89.12789127891278,
                26.81685562055621
              ],
              [
                89.05589055890562,
                26.651950976509767
              ],
              [
                89.05589055890562,
                26.601611664116646
              ],
              [
                89.12789127891278,
                26.601611664116646
              ],
              [
                89.12789127891278,
                26.521763099630988
              ],
              [
                89.27189271892718,
                26.488782170821707
              ],
              [
                89.3438934389344,
                26.495725524255235
              ],
              [
                89.37989379893799,
                26.462744595445955
              ],
              [
                89.45189451894521,
                26.488782170821707
              ],
              [
                89.52389523895238,
                26.480102979029795
              ],
              [
                89.55989559895602,
                26.41414112141122
              ],
              [
                89.5958959589596,
                26.431499504995045
              ],
              [
                89.63189631896319,
                26.389839384393838
              ],
              [
                89.66789667896683,
                26.438442858428587
              ],
              [
                89.70389703897041,
                26.422820313203133
              ],
              [
                89.77589775897758,
                26.462744595445955
              ],
              [
                89.88389883898839,
                26.462744595445955
              ]
            ]
          ]
        ]
      }
    },
    {
      "id": 3805,
      "type": "Feature",
      "properties": {
        "id": "IN_ADM2_76128533B25835998628545",
        "name": "Dhubri",
        "cntr_code": "FRI",
        "__source": "detail"
      },
      "geometry": {
        "type": "MultiPolygon",
        "coordinates": [
          [
            [
              [
                90.3519035190352,
                26.36553764737647
              ],
              [
                90.3519035190352,
                26.381160192601925
              ],
              [
                90.32747470331846,
                26.381160192601925
              ],
              [
                90.31590315903162,
                26.381160192601925
              ],
              [
                90.3519035190352,
                26.36553764737647
              ]
            ]
          ],
          [
            [
              [
                90.3519035190352,
                26.36553764737647
              ],
              [
                90.27990279902798,
                26.316934173341735
              ],
              [
                90.20790207902081,
                26.32561336513365
              ],
              [
                90.20790207902081,
                26.36553764737647
              ],
              [
                90.09990099901,
                26.32561336513365
              ],
              [
                90.13590135901359,
                26.217991386913866
              ],
              [
                90.13590135901359,
                26.21104803348034
              ],
              [
                90.13590135901359,
                26.1936896498965
              ],
              [
                90.06390063900642,
                26.185010458104585
              ],
              [
                90.06390063900642,
                26.21104803348034
              ],
              [
                90.02790027900278,
                26.20236884168841
              ],
              [
                90.02790027900278,
                26.242293123931233
              ],
              [
                89.91989919899203,
                26.1936896498965
              ],
              [
                89.91989919899203,
                26.153765367653676
              ],
              [
                89.88389883898839,
                26.167652074520745
              ],
              [
                89.8478984789848,
                26.25097231572316
              ],
              [
                89.91989919899203,
                26.381160192601925
              ],
              [
                89.88389883898839,
                26.431499504995045
              ],
              [
                89.84913987070905,
                26.41557767729401
              ],
              [
                89.84713251387835,
                26.414658179645627
              ],
              [
                89.81189811898122,
                26.398518576185765
              ],
              [
                89.82989829898303,
                26.394178980289805
              ],
              [
                89.88389883898839,
                26.381160192601925
              ],
              [
                89.81189811898122,
                26.381160192601925
              ],
              [
                89.81189811898122,
                26.374216839168383
              ],
              [
                89.77589775897758,
                26.356858455584558
              ],
              [
                89.77589775897758,
                26.290896597965983
              ],
              [
                89.739897398974,
                26.30825498154981
              ],
              [
                89.739897398974,
                26.268330699306986
              ],
              [
                89.7128971289713,
                26.26182130546305
              ],
              [
                89.70389703897041,
                26.259651507515073
              ],
              [
                89.739897398974,
                26.242293123931233
              ],
              [
                89.70389703897041,
                26.217991386913866
              ],
              [
                89.739897398974,
                26.21104803348034
              ],
              [
                89.70389703897041,
                26.17633126631266
              ],
              [
                89.739897398974,
                26.17633126631266
              ],
              [
                89.739897398974,
                26.160708721087204
              ],
              [
                89.77589775897758,
                26.103426055260556
              ],
              [
                89.81189811898122,
                26.0878035100351
              ],
              [
                89.77589775897758,
                26.03746419764198
              ],
              [
                89.81189811898122,
                26.03746419764198
              ],
              [
                89.81189811898122,
                25.98886072360723
              ],
              [
                89.8478984789848,
                25.98018153181532
              ],
              [
                89.8478984789848,
                26.0131624606246
              ],
              [
                89.88389883898839,
                25.98018153181532
              ],
              [
                89.81189811898122,
                25.947200603006024
              ],
              [
                89.88389883898839,
                25.947200603006024
              ],
              [
                89.88389883898839,
                25.89884510587962
              ],
              [
                89.88389883898839,
                25.89859712897129
              ],
              [
                90.09990099901,
                26.046143389433894
              ],
              [
                90.17190171901723,
                26.07044512645126
              ],
              [
                90.20790207902081,
                26.11904860048601
              ],
              [
                90.2439024390244,
                26.153765367653676
              ],
              [
                90.2439024390244,
                26.167652074520745
              ],
              [
                90.38790387903879,
                26.17633126631266
              ],
              [
                90.38790387903879,
                26.224934740347408
              ],
              [
                90.4959049590496,
                26.275274052740528
              ],
              [
                90.4959049590496,
                26.33255671856719
              ],
              [
                90.42390423904237,
                26.339500072000718
              ],
              [
                90.42390423904237,
                26.36553764737647
              ],
              [
                90.38790387903879,
                26.32561336513365
              ],
              [
                90.3601321727503,
                26.336325967573963
              ],
              [
                90.3519035190352,
                26.339500072000718
              ],
              [
                90.3519035190352,
                26.36553764737647
              ]
            ]
          ]
        ]
      }
    },
    {
      "id": 3813,
      "type": "Feature",
      "properties": {
        "id": "IN_ADM2_76128533B27432148084533",
        "name": "Katihar",
        "cntr_code": "FRI",
        "__source": "detail"
      },
      "geometry": {
        "type": "Polygon",
        "coordinates": [
          [
            [
              87.8318783187832,
              25.23724271442714
            ],
            [
              87.86787867878678,
              25.25112942129421
            ],
            [
              87.86787867878678,
              25.294525380253802
            ],
            [
              87.79587795877961,
              25.334449662496624
            ],
            [
              87.79587795877961,
              25.365694752947533
            ],
            [
              87.75987759877597,
              25.40735487354874
            ],
            [
              87.79587795877961,
              25.44033580235802
            ],
            [
              87.8318783187832,
              25.431656610566108
            ],
            [
              87.86787867878678,
              25.46463753937539
            ],
            [
              87.86787867878678,
              25.513241013410138
            ],
            [
              87.90387903879042,
              25.497618468184683
            ],
            [
              87.939879398794,
              25.53927858878589
            ],
            [
              88.0838808388084,
              25.480260084600843
            ],
            [
              88.01188011880117,
              25.587882062820626
            ],
            [
              88.0838808388084,
              25.63648553685536
            ],
            [
              88.04788047880481,
              25.63648553685536
            ],
            [
              88.04788047880481,
              25.68508901089011
            ],
            [
              87.97587975879759,
              25.726749131491317
            ],
            [
              87.939879398794,
              25.768409252092525
            ],
            [
              87.90387903879042,
              25.768409252092525
            ],
            [
              87.939879398794,
              25.81701272612726
            ],
            [
              87.86787867878678,
              25.8343711097111
            ],
            [
              87.939879398794,
              25.84825781657817
            ],
            [
              87.82567136016189,
              25.875791804331836
            ],
            [
              87.79587795877961,
              25.882974583745835
            ],
            [
              87.81551451878157,
              25.864038165290744
            ],
            [
              87.8318783187832,
              25.84825781657817
            ],
            [
              87.8012113454468,
              25.83642839961733
            ],
            [
              87.79587795877961,
              25.8343711097111
            ],
            [
              87.82437824378245,
              25.80001597553476
            ],
            [
              87.8318783187832,
              25.790975150751507
            ],
            [
              87.79587795877961,
              25.751050868508685
            ],
            [
              87.72387723877239,
              25.768409252092525
            ],
            [
              87.65187651876522,
              25.693768202682023
            ],
            [
              87.54387543875441,
              25.68508901089011
            ],
            [
              87.579875798758,
              25.6538439204392
            ],
            [
              87.54387543875441,
              25.676409819098183
            ],
            [
              87.50787507875077,
              25.6538439204392
            ],
            [
              87.47187471874719,
              25.676409819098183
            ],
            [
              87.25587255872557,
              25.70244739447395
            ],
            [
              87.29187291872921,
              25.63648553685536
            ],
            [
              87.25587255872557,
              25.619127153271535
            ],
            [
              87.29187291872921,
              25.563580325803258
            ],
            [
              87.25587255872557,
              25.563580325803258
            ],
            [
              87.24387243872437,
              25.541593039930383
            ],
            [
              87.21987219872199,
              25.497618468184683
            ],
            [
              87.25587255872557,
              25.45769418594186
            ],
            [
              87.1838718387184,
              25.416034065340654
            ],
            [
              87.21987219872199,
              25.374373944739446
            ],
            [
              87.25587255872557,
              25.365694752947533
            ],
            [
              87.25587255872557,
              25.35875139951399
            ],
            [
              87.29187291872921,
              25.4004115201152
            ],
            [
              87.36387363873638,
              25.42297741877418
            ],
            [
              87.4358743587436,
              25.365694752947533
            ],
            [
              87.54387543875441,
              25.35875139951399
            ],
            [
              87.61587615876158,
              25.299732895328958
            ],
            [
              87.8318783187832,
              25.23724271442714
            ]
          ]
        ]
      }
    },
    {
      "id": 3837,
      "type": "Feature",
      "properties": {
        "id": "IN_ADM2_76128533B30151252629779",
        "name": "West District",
        "cntr_code": "FRI",
        "__source": "detail"
      },
      "geometry": {
        "type": "Polygon",
        "coordinates": [
          [
            [
              88.11988119881198,
              27.618812942129424
            ],
            [
              88.04788047880481,
              27.495568418684186
            ],
            [
              88.0838808388084,
              27.42960656106561
            ],
            [
              88.04788047880481,
              27.405304824048244
            ],
            [
              88.0838808388084,
              27.330663774637742
            ],
            [
              88.0163246076905,
              27.223170377037103
            ],
            [
              88.01188011880117,
              27.216098442984432
            ],
            [
              88.04788047880479,
              27.21175884708847
            ],
            [
              88.0838808388084,
              27.207419251192505
            ],
            [
              88.0838808388084,
              27.198740059400592
            ],
            [
              88.0838808388084,
              27.14145739357393
            ],
            [
              88.15588155881562,
              27.118891494914948
            ],
            [
              88.1918819188192,
              27.134514040140402
            ],
            [
              88.21965362510768,
              27.13272860640035
            ],
            [
              88.29988299883001,
              27.12757068670686
            ],
            [
              88.3358833588336,
              27.193532544325436
            ],
            [
              88.26388263882637,
              27.282060300603007
            ],
            [
              88.29988299883001,
              27.306362037620374
            ],
            [
              88.29988299883001,
              27.317355680556844
            ],
            [
              88.29988299883001,
              27.330663774637742
            ],
            [
              88.37188371883718,
              27.37926724867249
            ],
            [
              88.37188371883718,
              27.396625632256317
            ],
            [
              88.33188331883319,
              27.406269178691787
            ],
            [
              88.29988299883001,
              27.413984015840157
            ],
            [
              88.29988299883001,
              27.420927369273684
            ],
            [
              88.29988299883001,
              27.495568418684186
            ],
            [
              88.29988299883001,
              27.502511772117714
            ],
            [
              88.27931136454221,
              27.509455125551263
            ],
            [
              88.22788227882279,
              27.526813509135096
            ],
            [
              88.22788227882279,
              27.577152821528216
            ],
            [
              88.1918819188192,
              27.601454558545583
            ],
            [
              88.11988119881198,
              27.59277536675367
            ],
            [
              88.11988119881198,
              27.618812942129424
            ]
          ]
        ]
      }
    },
    {
      "id": 3851,
      "type": "Feature",
      "properties": {
        "id": "IN_ADM2_76128533B32499449492865",
        "name": "Purnia",
        "cntr_code": "FRI",
        "__source": "detail"
      },
      "geometry": {
        "type": "Polygon",
        "coordinates": [
          [
            [
              87.25587255872557,
              25.45769418594186
            ],
            [
              87.21987219872199,
              25.497618468184683
            ],
            [
              87.21987219872199,
              25.530599396993964
            ],
            [
              87.24387243872437,
              25.541593039930383
            ],
            [
              87.29187291872921,
              25.563580325803258
            ],
            [
              87.25587255872557,
              25.619127153271535
            ],
            [
              87.29187291872921,
              25.63648553685536
            ],
            [
              87.25587255872557,
              25.70244739447395
            ],
            [
              87.47187471874719,
              25.676409819098183
            ],
            [
              87.50787507875077,
              25.6538439204392
            ],
            [
              87.54387543875441,
              25.676409819098183
            ],
            [
              87.579875798758,
              25.6538439204392
            ],
            [
              87.54387543875441,
              25.68508901089011
            ],
            [
              87.65187651876522,
              25.693768202682023
            ],
            [
              87.72387723877239,
              25.768409252092525
            ],
            [
              87.79587795877961,
              25.751050868508685
            ],
            [
              87.79587795877961,
              25.768409252092525
            ],
            [
              87.82437824378245,
              25.80001597553476
            ],
            [
              87.8318783187832,
              25.808333534335347
            ],
            [
              87.8012113454468,
              25.83642839961733
            ],
            [
              87.79587795877961,
              25.841314463144627
            ],
            [
              87.81551451878157,
              25.864038165290744
            ],
            [
              87.82567136016189,
              25.875791804331836
            ],
            [
              87.8318783187832,
              25.882974583745835
            ],
            [
              87.80535173772792,
              25.918787669876696
            ],
            [
              87.79587795877961,
              25.93157805778057
            ],
            [
              87.8318783187832,
              25.93157805778057
            ],
            [
              87.79587795877961,
              25.98886072360723
            ],
            [
              87.8318783187832,
              26.004483268832686
            ],
            [
              87.86787867878678,
              26.103426055260556
            ],
            [
              87.75987759877597,
              26.103426055260556
            ],
            [
              87.6878768787688,
              26.145086175861763
            ],
            [
              87.65187651876522,
              26.0878035100351
            ],
            [
              87.61587615876158,
              26.0878035100351
            ],
            [
              87.61587615876158,
              26.079124318243174
            ],
            [
              87.61587615876158,
              26.03052084420844
            ],
            [
              87.50787507875077,
              25.971502340023406
            ],
            [
              87.4358743587436,
              25.98886072360723
            ],
            [
              87.39987399874002,
              25.947200603006024
            ],
            [
              87.36387363873638,
              25.971502340023406
            ],
            [
              87.29187291872921,
              25.947200603006024
            ],
            [
              87.25587255872557,
              25.971502340023406
            ],
            [
              87.21987219872199,
              25.93157805778057
            ],
            [
              87.11187111871118,
              25.940257249572497
            ],
            [
              87.10467104671045,
              25.93852141121411
            ],
            [
              87.0758707587076,
              25.931578057780584
            ],
            [
              87.00387003870037,
              25.914219674196744
            ],
            [
              87.03987039870401,
              25.825691917919173
            ],
            [
              87.03987039870401,
              25.784031797317965
            ],
            [
              87.03987039870401,
              25.719805778057776
            ],
            [
              87.0758707587076,
              25.676409819098183
            ],
            [
              87.03987039870401,
              25.63648553685536
            ],
            [
              87.0758707587076,
              25.52192020520205
            ],
            [
              87.11187111871118,
              25.52192020520205
            ],
            [
              87.0758707587076,
              25.44033580235802
            ],
            [
              87.25587255872557,
              25.45769418594186
            ]
          ]
        ]
      }
    },
    {
      "id": 3911,
      "type": "Feature",
      "properties": {
        "id": "IN_ADM2_76128533B40226077866964",
        "name": "Gorakhpur",
        "cntr_code": "FRI",
        "__source": "detail"
      },
      "geometry": {
        "type": "MultiPolygon",
        "coordinates": [
          [
            [
              [
                83.07983079830797,
                26.405461929619293
              ],
              [
                83.15183151831519,
                26.381160192601925
              ],
              [
                83.15941054147383,
                26.382073791737913
              ],
              [
                83.22383223832242,
                26.389839384393838
              ],
              [
                83.33183331833317,
                26.34817926379263
              ],
              [
                83.40383403834039,
                26.275274052740528
              ],
              [
                83.5118351183512,
                26.275274052740528
              ],
              [
                83.54783547835478,
                26.275274052740528
              ],
              [
                83.61983619836201,
                26.242293123931233
              ],
              [
                83.61983619836201,
                26.275274052740528
              ],
              [
                83.69183691836918,
                26.290896597965983
              ],
              [
                83.6826060568298,
                26.297572899344377
              ],
              [
                83.67598321029453,
                26.30236293105092
              ],
              [
                83.65583655836559,
                26.316934173341735
              ],
              [
                83.61983619836201,
                26.299575789757895
              ],
              [
                83.61983619836201,
                26.32561336513365
              ],
              [
                83.58383583835837,
                26.34817926379263
              ],
              [
                83.61983619836201,
                26.374216839168383
              ],
              [
                83.58383583835837,
                26.36553764737647
              ],
              [
                83.58383583835837,
                26.381160192601925
              ],
              [
                83.54783547835478,
                26.356858455584558
              ],
              [
                83.54783547835478,
                26.381160192601925
              ],
              [
                83.5118351183512,
                26.381160192601925
              ],
              [
                83.54783547835478,
                26.398518576185765
              ],
              [
                83.47583475834762,
                26.398518576185765
              ],
              [
                83.5118351183512,
                26.41414112141122
              ],
              [
                83.47583475834762,
                26.462744595445955
              ],
              [
                83.47583475834762,
                26.488782170821707
              ],
              [
                83.58383583835837,
                26.513083907839075
              ],
              [
                83.61983619836201,
                26.57904576545765
              ],
              [
                83.61983619836201,
                26.651950976509767
              ],
              [
                83.61983619836201,
                26.750893762937622
              ],
              [
                83.61983619836201,
                26.75957295472955
              ],
              [
                83.58383583835837,
                26.76478046980469
              ],
              [
                83.58383583835837,
                26.790818045180444
              ],
              [
                83.58383583835837,
                26.81685562055621
              ],
              [
                83.54783547835478,
                26.848100711007106
              ],
              [
                83.54783547835478,
                26.856779902799033
              ],
              [
                83.54783547835478,
                26.8810816398164
              ],
              [
                83.47583475834762,
                26.92274176041761
              ],
              [
                83.47583475834762,
                26.96266604266043
              ],
              [
                83.43983439834398,
                26.97828858788587
              ],
              [
                83.33183331833317,
                26.986967779677798
              ],
              [
                83.39940322480147,
                27.08633784939387
              ],
              [
                83.40383403834039,
                27.092853919539195
              ],
              [
                83.33183331833317,
                27.092853919539195
              ],
              [
                83.29583295832958,
                27.052929637296373
              ],
              [
                83.18783187831878,
                27.085910566105653
              ],
              [
                83.15183151831519,
                27.12757068670686
              ],
              [
                83.14032327881104,
                27.132009851996717
              ],
              [
                83.139831398314,
                27.13219958899588
              ],
              [
                83.11583115831161,
                27.14145739357393
              ],
              [
                83.15183151831519,
                27.118891494914948
              ],
              [
                83.11583115831161,
                27.110212303123035
              ],
              [
                83.15183151831519,
                27.052929637296373
              ],
              [
                83.11583115831161,
                27.052929637296373
              ],
              [
                83.15183151831519,
                27.04425044550446
              ],
              [
                83.15183151831519,
                27.004326163261638
              ],
              [
                83.22383223832242,
                27.019948708487078
              ],
              [
                83.22383223832242,
                26.8810816398164
              ],
              [
                83.15183151831519,
                26.889760831608314
              ],
              [
                83.11583115831161,
                26.808176428764284
              ],
              [
                83.15183151831519,
                26.750893762937622
              ],
              [
                83.07983079830797,
                26.702290288902887
              ],
              [
                83.11583115831161,
                26.684931905319047
              ],
              [
                83.11583115831161,
                26.61029085590856
              ],
              [
                83.15183151831519,
                26.561687381873824
              ],
              [
                83.22383223832242,
                26.521763099630988
              ],
              [
                83.18783187831878,
                26.488782170821707
              ],
              [
                83.15183151831519,
                26.513083907839075
              ],
              [
                83.11583115831161,
                26.488782170821707
              ],
              [
                83.11583115831161,
                26.431499504995045
              ],
              [
                83.07983079830797,
                26.405461929619293
              ]
            ]
          ],
          [
            [
              [
                83.58383583835837,
                26.381160192601925
              ],
              [
                83.58383583835837,
                26.398518576185765
              ],
              [
                83.54783547835478,
                26.389839384393838
              ],
              [
                83.58383583835837,
                26.381160192601925
              ]
            ]
          ]
        ]
      }
    },
    {
      "id": 4130,
      "type": "Feature",
      "properties": {
        "id": "IN_ADM2_76128533B65773363805797",
        "name": "Kishanganj",
        "cntr_code": "FRI",
        "__source": "detail"
      },
      "geometry": {
        "type": "MultiPolygon",
        "coordinates": [
          [
            [
              [
                87.8318783187832,
                26.03746419764198
              ],
              [
                87.939879398794,
                26.09474686346863
              ],
              [
                87.939879398794,
                26.07044512645126
              ],
              [
                87.97587975879759,
                26.0878035100351
              ],
              [
                87.97587975879759,
                26.153765367653676
              ],
              [
                88.01188011880117,
                26.145086175861763
              ],
              [
                88.04788047880481,
                26.17633126631266
              ],
              [
                88.0838808388084,
                26.17633126631266
              ],
              [
                88.15588155881562,
                26.25097231572316
              ],
              [
                88.29988299883001,
                26.33255671856719
              ],
              [
                88.26388263882637,
                26.381160192601925
              ],
              [
                88.22788227882279,
                26.389839384393838
              ],
              [
                88.26388263882637,
                26.422820313203133
              ],
              [
                88.23757468343914,
                26.45833823653621
              ],
              [
                88.22788227882279,
                26.471423787237867
              ],
              [
                88.1918819188192,
                26.488782170821707
              ],
              [
                88.22788227882279,
                26.553008190081897
              ],
              [
                88.15588155881562,
                26.513083907839075
              ],
              [
                88.11988119881198,
                26.544328998289984
              ],
              [
                88.0838808388084,
                26.431499504995045
              ],
              [
                88.01188011880117,
                26.389839384393838
              ],
              [
                88.01188011880117,
                26.36553764737647
              ],
              [
                87.97587975879759,
                26.36553764737647
              ],
              [
                87.97587975879759,
                26.374216839168383
              ],
              [
                87.97587975879759,
                26.389839384393838
              ],
              [
                87.86787867878678,
                26.488782170821707
              ],
              [
                87.84710924032318,
                26.459740259825676
              ],
              [
                87.8318783187832,
                26.438442858428587
              ],
              [
                87.79587795877961,
                26.471423787237867
              ],
              [
                87.78267782677828,
                26.450420143101432
              ],
              [
                87.75987759877597,
                26.41414112141122
              ],
              [
                87.73781286199959,
                26.42158842791654
              ],
              [
                87.6878768787688,
                26.438442858428587
              ],
              [
                87.66344806305209,
                26.405461929619293
              ],
              [
                87.65187651876522,
                26.389839384393838
              ],
              [
                87.579875798758,
                26.381160192601925
              ],
              [
                87.61587615876158,
                26.34817926379263
              ],
              [
                87.65187651876522,
                26.33255671856719
              ],
              [
                87.65187651876522,
                26.275274052740528
              ],
              [
                87.6878768787688,
                26.224934740347408
              ],
              [
                87.6878768787688,
                26.145086175861763
              ],
              [
                87.75987759877597,
                26.103426055260556
              ],
              [
                87.86787867878678,
                26.103426055260556
              ],
              [
                87.8318783187832,
                26.054822581225807
              ],
              [
                87.8318783187832,
                26.03746419764198
              ]
            ]
          ],
          [
            [
              [
                87.8318783187832,
                25.947200603006024
              ],
              [
                87.8318783187832,
                26.004483268832686
              ],
              [
                87.79587795877961,
                25.98886072360723
              ],
              [
                87.8318783187832,
                25.947200603006024
              ]
            ]
          ]
        ]
      }
    },
    {
      "id": 4155,
      "type": "Feature",
      "properties": {
        "id": "IN_ADM2_76128533B67639510673366",
        "name": "East District",
        "cntr_code": "FRI",
        "__source": "detail"
      },
      "geometry": {
        "type": "Polygon",
        "coordinates": [
          [
            [
              88.51588515885157,
              27.37926724867249
            ],
            [
              88.4438844388444,
              27.27338110881108
            ],
            [
              88.51588515885157,
              27.242136018360185
            ],
            [
              88.51588515885157,
              27.198740059400592
            ],
            [
              88.51588515885157,
              27.193532544325436
            ],
            [
              88.51974234028054,
              27.193532544325436
            ],
            [
              88.5878858788588,
              27.193532544325436
            ],
            [
              88.65988659886602,
              27.15881577715777
            ],
            [
              88.69588695886961,
              27.184853352533523
            ],
            [
              88.73188731887319,
              27.134514040140402
            ],
            [
              88.74419123938075,
              27.144599480728985
            ],
            [
              88.80388803888042,
              27.193532544325436
            ],
            [
              88.80388803888042,
              27.250815210152098
            ],
            [
              88.91188911889122,
              27.27338110881108
            ],
            [
              88.91188911889122,
              27.32198458284583
            ],
            [
              88.7818579678334,
              27.41132844223218
            ],
            [
              88.76788767887678,
              27.420927369273684
            ],
            [
              88.51588515885157,
              27.37926724867249
            ]
          ]
        ]
      }
    },
    {
      "id": 4237,
      "type": "Feature",
      "properties": {
        "id": "IN_ADM2_76128533B78458325839103",
        "name": "Kalimpong",
        "cntr_code": "FRI",
        "__source": "detail"
      },
      "geometry": {
        "type": "Polygon",
        "coordinates": [
          [
            [
              88.4438844388444,
              27.07723137431374
            ],
            [
              88.40788407884082,
              27.011269516695165
            ],
            [
              88.40788407884082,
              26.986967779677798
            ],
            [
              88.4438844388444,
              26.96266604266043
            ],
            [
              88.50426299538586,
              26.873871760020744
            ],
            [
              88.51588515885157,
              26.856779902799033
            ],
            [
              88.62388623886238,
              26.8810816398164
            ],
            [
              88.65988659886602,
              26.96266604266043
            ],
            [
              88.65988659886602,
              26.92274176041761
            ],
            [
              88.76788767887678,
              26.92274176041761
            ],
            [
              88.76788767887678,
              26.96266604266043
            ],
            [
              88.80388803888042,
              26.986967779677798
            ],
            [
              88.839888398884,
              26.974816911169114
            ],
            [
              88.8710238453736,
              26.964308051918355
            ],
            [
              88.87588875888758,
              26.96266604266043
            ],
            [
              88.87588875888758,
              26.967005638556373
            ],
            [
              88.87588875888758,
              27.110212303123035
            ],
            [
              88.78743073145017,
              27.12514051300513
            ],
            [
              88.73188731887319,
              27.134514040140402
            ],
            [
              88.69588695886961,
              27.184853352533523
            ],
            [
              88.65988659886602,
              27.15881577715777
            ],
            [
              88.5878858788588,
              27.193532544325436
            ],
            [
              88.52532787622958,
              27.185991607194758
            ],
            [
              88.51588515885157,
              27.184853352533523
            ],
            [
              88.55188551885522,
              27.150136585365857
            ],
            [
              88.4438844388444,
              27.07723137431374
            ]
          ]
        ]
      }
    },
    {
      "id": 4317,
      "type": "Feature",
      "properties": {
        "id": "IN_ADM2_76128533B88623139855224",
        "name": "Mau",
        "cntr_code": "FRI",
        "__source": "detail"
      },
      "geometry": {
        "type": "Polygon",
        "coordinates": [
          [
            [
              83.5118351183512,
              26.275274052740528
            ],
            [
              83.43983439834398,
              26.160708721087204
            ],
            [
              83.43983439834398,
              26.103426055260556
            ],
            [
              83.40383403834039,
              26.06176593465935
            ],
            [
              83.40383403834039,
              26.046143389433894
            ],
            [
              83.33183331833317,
              26.03746419764198
            ],
            [
              83.40383403834039,
              26.021841652416526
            ],
            [
              83.33183331833317,
              25.99753991539916
            ],
            [
              83.33183331833317,
              25.93157805778057
            ],
            [
              83.40383403834039,
              25.947200603006024
            ],
            [
              83.40383403834039,
              25.922898865988657
            ],
            [
              83.33183331833317,
              25.891653775537748
            ],
            [
              83.33183331833317,
              25.8343711097111
            ],
            [
              83.34623346233462,
              25.820484402844027
            ],
            [
              83.34756842826566,
              25.819197035123263
            ],
            [
              83.3558335583356,
              25.811226598265975
            ],
            [
              83.36783367833681,
              25.79965434254342
            ],
            [
              83.37503375033752,
              25.80659769597695
            ],
            [
              83.40383403834039,
              25.8343711097111
            ],
            [
              83.47583475834762,
              25.8343711097111
            ],
            [
              83.58383583835837,
              25.882974583745835
            ],
            [
              83.61983619836201,
              25.865616200161995
            ],
            [
              83.65583655836559,
              25.89859712897129
            ],
            [
              83.72783727837282,
              25.856937008370082
            ],
            [
              83.73850405170721,
              25.86670913542468
            ],
            [
              83.79983799837999,
              25.922898865988657
            ],
            [
              83.79983799837999,
              25.98018153181532
            ],
            [
              83.79983799837999,
              25.98886072360723
            ],
            [
              83.78881748001155,
              25.983546932714223
            ],
            [
              83.7638376383764,
              25.971502340023406
            ],
            [
              83.7638376383764,
              25.99117517475174
            ],
            [
              83.7638376383764,
              26.004483268832686
            ],
            [
              83.69183691836918,
              26.03052084420844
            ],
            [
              83.69183691836918,
              26.079124318243174
            ],
            [
              83.79983799837999,
              26.103426055260556
            ],
            [
              83.79983799837999,
              26.136406984069836
            ],
            [
              83.7638376383764,
              26.160708721087204
            ],
            [
              83.83583835838357,
              26.185010458104585
            ],
            [
              83.83230891132439,
              26.18977550457858
            ],
            [
              83.79983799837999,
              26.23361393213932
            ],
            [
              83.72783727837282,
              26.259651507515073
            ],
            [
              83.61983619836201,
              26.217991386913866
            ],
            [
              83.61983619836201,
              26.224934740347408
            ],
            [
              83.61983619836201,
              26.242293123931233
            ],
            [
              83.5118351183512,
              26.275274052740528
            ]
          ]
        ]
      }
    },
    {
      "id": 4342,
      "type": "Feature",
      "properties": {
        "id": "IN_ADM2_76128533B91480770176940",
        "name": "Kokrajhar",
        "cntr_code": "FRI",
        "__source": "detail"
      },
      "geometry": {
        "type": "Polygon",
        "coordinates": [
          [
            [
              90.38561274874613,
              26.347997698951847
            ],
            [
              90.42390423904237,
              26.36553764737647
            ],
            [
              90.38790387903879,
              26.398518576185765
            ],
            [
              90.42390423904237,
              26.4471220502205
            ],
            [
              90.45990459904601,
              26.462744595445955
            ],
            [
              90.42390423904237,
              26.495725524255235
            ],
            [
              90.42390423904237,
              26.561687381873824
            ],
            [
              90.38790387903879,
              26.618970047700472
            ],
            [
              90.42390423904237,
              26.72485618756187
            ],
            [
              90.42390423904237,
              26.8810816398164
            ],
            [
              90.42390423904237,
              26.896704185041855
            ],
            [
              90.3519035190352,
              26.896704185041855
            ],
            [
              90.27990279902798,
              26.848100711007106
            ],
            [
              90.21927061375881,
              26.848100711007106
            ],
            [
              90.20790207902081,
              26.848100711007106
            ],
            [
              90.20790207902081,
              26.84393469894698
            ],
            [
              90.20790207902081,
              26.77345966159662
            ],
            [
              90.13590135901359,
              26.750893762937622
            ],
            [
              89.88389883898839,
              26.72485618756187
            ],
            [
              89.88389883898839,
              26.716871331113307
            ],
            [
              89.88389883898839,
              26.707497803978043
            ],
            [
              89.88389883898839,
              26.462744595445955
            ],
            [
              89.88389883898839,
              26.455801242012413
            ],
            [
              89.88389883898839,
              26.431499504995045
            ],
            [
              89.91989919899203,
              26.36553764737647
            ],
            [
              89.8478984789848,
              26.25097231572316
            ],
            [
              89.88389883898839,
              26.167652074520745
            ],
            [
              89.91989919899203,
              26.153765367653676
            ],
            [
              89.91989919899203,
              26.1936896498965
            ],
            [
              90.02790027900278,
              26.242293123931233
            ],
            [
              90.02790027900278,
              26.20236884168841
            ],
            [
              90.06390063900642,
              26.21104803348034
            ],
            [
              90.06390063900642,
              26.185010458104585
            ],
            [
              90.13590135901359,
              26.21104803348034
            ],
            [
              90.13590135901359,
              26.217991386913866
            ],
            [
              90.13590135901359,
              26.282217406174055
            ],
            [
              90.09990099901,
              26.32561336513365
            ],
            [
              90.13590135901359,
              26.34817926379263
            ],
            [
              90.20790207902081,
              26.36553764737647
            ],
            [
              90.20790207902081,
              26.32561336513365
            ],
            [
              90.27990279902798,
              26.316934173341735
            ],
            [
              90.32747470331846,
              26.381160192601925
            ],
            [
              90.3519035190352,
              26.41414112141122
            ],
            [
              90.3519035190352,
              26.381160192601925
            ],
            [
              90.3519035190352,
              26.36553764737647
            ],
            [
              90.3519035190352,
              26.339500072000718
            ],
            [
              90.3519035190352,
              26.33255671856719
            ],
            [
              90.3601321727503,
              26.336325967573963
            ],
            [
              90.38561274874613,
              26.347997698951847
            ]
          ]
        ]
      }
    }
  ]
}
