{
  "type": "FeatureCollection",
  "features": [
    {
      "id": 10911,
      "type": "Feature",
      "properties": {
        "id": "AX",
        "name": "Aland",
        "cntr_code": "AX",
        "__source": "primary"
      },
      "geometry": {
        "type": "MultiPolygon",
        "coordinates": [
          [
            [
              [
                20.504000504000516,
                60.01653872883871
              ],
              [
                20.504000504000516,
                60.004387969687954
              ],
              [
                20.6120006120006,
                60.02174619704617
              ],
              [
                20.6120006120006,
                60.039104424404414
              ],
              [
                20.57600057600058,
                60.07382087912087
              ],
              [
                20.540000540000534,
                60.07382087912087
              ],
              [
                20.504000504000516,
                60.07382087912087
              ],
              [
                20.43200043200042,
                60.05646265176263
              ],
              [
                20.396000396000403,
                60.039104424404414
              ],
              [
                20.396000396000403,
                60.038410095310084
              ],
              [
                20.396000396000403,
                60.02174619704617
              ],
              [
                20.504000504000516,
                60.039104424404414
              ],
              [
                20.504000504000516,
                60.01653872883871
              ]
            ]
          ],
          [
            [
              [
                20.238320238320227,
                60.28541767061766
              ],
              [
                20.180000180000178,
                60.29947783477782
              ],
              [
                20.180000180000178,
                60.31683606213606
              ],
              [
                20.072000072000066,
                60.35155251685249
              ],
              [
                19.927999927999934,
                60.35155251685249
              ],
              [
                19.891999891999887,
                60.4036271989272
              ],
              [
                19.819999819999822,
                60.38626897156895
              ],
              [
                19.783999783999775,
                60.35155251685249
              ],
              [
                19.85599985599987,
                60.31683606213606
              ],
              [
                19.85599985599987,
                60.21268669798668
              ],
              [
                19.783999783999775,
                60.21268669798668
              ],
              [
                19.783999783999775,
                60.2821196074196
              ],
              [
                19.67599967599969,
                60.26476138006136
              ],
              [
                19.67599967599969,
                60.2300449253449
              ],
              [
                19.747999747999756,
                60.09117910647909
              ],
              [
                19.783999783999775,
                60.07382087912087
              ],
              [
                20.036000036000047,
                60.09117910647909
              ],
              [
                20.036000036000047,
                60.177970243270224
              ],
              [
                20.072000072000066,
                60.19532847062847
              ],
              [
                20.1094401094401,
                60.19532847062847
              ],
              [
                20.180000180000178,
                60.19532847062847
              ],
              [
                20.252000252000244,
                60.26476138006136
              ],
              [
                20.252000252000244,
                60.2821196074196
              ],
              [
                20.238320238320227,
                60.28541767061766
              ]
            ]
          ],
          [
            [
              [
                19.558999558999574,
                60.2300449253449
              ],
              [
                19.53199953199953,
                60.177970243270224
              ],
              [
                19.53199953199953,
                60.143253788553764
              ],
              [
                19.56799956799958,
                60.12589556119555
              ],
              [
                19.603999603999597,
                60.16061201591201
              ],
              [
                19.639999639999644,
                60.177970243270224
              ],
              [
                19.67599967599969,
                60.16061201591201
              ],
              [
                19.639999639999644,
                60.24740315270314
              ],
              [
                19.56799956799958,
                60.24740315270314
              ],
              [
                19.558999558999574,
                60.2300449253449
              ]
            ]
          ]
        ]
      }
    }
  ]
}
