{
  "type": "FeatureCollection",
  "features": [
    {
      "id": 249,
      "type": "Feature",
      "properties": {
        "id": "BGD-1806",
        "name": "Dhaka",
        "cntr_code": "BD",
        "__source": "detail"
      },
      "geometry": {
        "type": "Polygon",
        "coordinates": [
          [
            [
              89.8119898119898,
              25.374377225477218
            ],
            [
              89.8119898119898,
              25.40735785745784
            ],
            [
              89.7939897939898,
              25.39954665514665
            ],
            [
              89.77598977598979,
              25.391735452835448
            ],
            [
              89.73998973998977,
              25.325774188874178
            ],
            [
              89.73998973998977,
              25.24245469755469
            ],
            [
              89.66798966798967,
              25.16260685170684
            ],
            [
              89.66798966798967,
              24.966458882558868
            ],
            [
              89.7014697014697,
              24.821170519570515
            ],
            [
              89.70398970398969,
              24.81023483633483
            ],
            [
              89.8119898119898,
              24.719972054072045
            ],
            [
              89.73998973998977,
              24.360656747756735
            ],
            [
              89.77598977598979,
              24.27733725643725
            ],
            [
              89.8119898119898,
              24.18881029691029
            ],
            [
              89.8119898119898,
              24.16277295587294
            ],
            [
              89.8119898119898,
              24.081189287289277
            ],
            [
              89.70398970398969,
              23.983983214083196
            ],
            [
              89.70398970398969,
              23.85206068616067
            ],
            [
              89.52398952398954,
              23.820815876915873
            ],
            [
              89.34398934398934,
              23.91802195012194
            ],
            [
              89.34398934398934,
              23.85206068616067
            ],
            [
              89.30798930798932,
              23.728817271917265
            ],
            [
              89.34398934398934,
              23.671535121635117
            ],
            [
              89.41598941598943,
              23.671535121635117
            ],
            [
              89.52398952398954,
              23.5413484164484
            ],
            [
              89.48798948798947,
              23.484066266166252
            ],
            [
              89.52398952398954,
              23.50836778446778
            ],
            [
              89.59598959598958,
              23.475387152487144
            ],
            [
              89.63198963198965,
              23.369501965601955
            ],
            [
              89.59598959598958,
              23.386860192960185
            ],
            [
              89.59598959598958,
              23.352143738243726
            ],
            [
              89.63198963198965,
              23.28618247428247
            ],
            [
              89.66798966798967,
              23.28618247428247
            ],
            [
              89.63198963198965,
              23.23757943767943
            ],
            [
              89.66798966798967,
              23.221957033057024
            ],
            [
              89.70398970398969,
              23.173353996453983
            ],
            [
              89.77598977598979,
              23.173353996453983
            ],
            [
              89.70398970398969,
              23.123015137115132
            ],
            [
              89.66798966798967,
              23.13169425079424
            ],
            [
              89.66798966798967,
              23.107392732492727
            ],
            [
              89.8119898119898,
              22.935546281646268
            ],
            [
              89.91998991998992,
              22.86958501768501
            ],
            [
              89.99198999199001,
              22.886943245043227
            ],
            [
              90.13599013599014,
              23.06573298683297
            ],
            [
              90.20799020799024,
              23.06573298683297
            ],
            [
              90.27999027999027,
              22.9754702045702
            ],
            [
              90.31599031599029,
              23.017129950229943
            ],
            [
              90.27999027999027,
              23.041431468531457
            ],
            [
              90.35199035199037,
              23.06573298683297
            ],
            [
              90.4239904239904,
              23.02580906390905
            ],
            [
              90.45999045999048,
              23.06573298683297
            ],
            [
              90.56799056799059,
              23.116071846171835
            ],
            [
              90.56799056799059,
              23.0830912141912
            ],
            [
              90.60399060399061,
              23.140373364473348
            ],
            [
              90.60399060399061,
              23.215013742113726
            ],
            [
              90.63999063999063,
              23.19765551475551
            ],
            [
              90.56799056799059,
              23.28618247428247
            ],
            [
              90.4239904239904,
              23.329578042678037
            ],
            [
              90.24399024399025,
              23.466708038808022
            ],
            [
              90.56799056799059,
              23.386860192960185
            ],
            [
              90.56799056799059,
              23.5413484164484
            ],
            [
              90.4959904959905,
              23.583008162108158
            ],
            [
              90.53199053199052,
              23.565649934749928
            ],
            [
              90.63999063999063,
              23.60730968040967
            ],
            [
              90.63999063999063,
              23.59863056673055
            ],
            [
              90.60399060399061,
              23.556970821070806
            ],
            [
              90.60399060399061,
              23.492745379845374
            ],
            [
              90.71199071199072,
              23.50836778446778
            ],
            [
              90.6759906759907,
              23.550027530127522
            ],
            [
              90.78399078399076,
              23.622932085032076
            ],
            [
              90.71199071199072,
              23.720138158238143
            ],
            [
              90.78399078399076,
              23.85206068616067
            ],
            [
              90.89199089199087,
              23.87809802719802
            ],
            [
              91.03599103599106,
              24.089868400968385
            ],
            [
              90.99999099999098,
              24.16277295587294
            ],
            [
              91.14399114399117,
              24.254771560871546
            ],
            [
              91.25199125199123,
              24.37627915237914
            ],
            [
              91.21599121599121,
              24.417938898038884
            ],
            [
              91.25199125199123,
              24.466541934641924
            ],
            [
              91.17999117999119,
              24.48216433926433
            ],
            [
              91.25199125199123,
              24.556804716904708
            ],
            [
              91.17999117999119,
              24.614086867186856
            ],
            [
              91.21599121599121,
              24.680048131148126
            ],
            [
              91.14399114399117,
              24.695670535770518
            ],
            [
              91.14399114399117,
              24.883139391239382
            ],
            [
              90.96399096399097,
              24.883139391239382
            ],
            [
              90.89199089199087,
              24.973402173502166
            ],
            [
              90.96399096399097,
              25.054985842085827
            ],
            [
              90.92799092799095,
              25.16260685170684
            ],
            [
              90.47871047871047,
              25.155837143037132
            ],
            [
              90.35199035199037,
              25.153927738027733
            ],
            [
              89.91998991998992,
              25.294529379629367
            ],
            [
              89.8119898119898,
              25.28585026595026
            ],
            [
              89.8119898119898,
              25.294529379629367
            ],
            [
              89.8119898119898,
              25.374377225477218
            ]
          ]
        ]
      }
    },
    {
      "id": 250,
      "type": "Feature",
      "properties": {
        "id": "BGD-2432",
        "name": "Khulna",
        "cntr_code": "BD",
        "__source": "detail"
      },
      "geometry": {
        "type": "MultiPolygon",
        "coordinates": [
          [
            [
              [
                89.05598905598907,
                22.175255923355905
              ],
              [
                89.12798912798911,
                21.814204794304786
              ],
              [
                89.16398916398919,
                21.78122416232415
              ],
              [
                89.1999891999892,
                21.814204794304786
              ],
              [
                89.23598923598922,
                21.65103745713745
              ],
              [
                89.30798930798932,
                21.67533897543896
              ],
              [
                89.2719892719893,
                21.69964049374049
              ],
              [
                89.2719892719893,
                21.82114808524807
              ],
              [
                89.30798930798932,
                21.807261503361488
              ],
              [
                89.34398934398934,
                21.895788462888447
              ],
              [
                89.34398934398934,
                21.979107954207947
              ],
              [
                89.37998937998935,
                21.90446757656757
              ],
              [
                89.37998937998935,
                21.715262898362894
              ],
              [
                89.45198945198945,
                21.78122416232415
              ],
              [
                89.45198945198945,
                21.85586453996453
              ],
              [
                89.52398952398954,
                21.961749726849717
              ],
              [
                89.48798948798947,
                22.027710990810974
              ],
              [
                89.52398952398954,
                22.076314027414014
              ],
              [
                89.52398952398954,
                21.98605124515123
              ],
              [
                89.59598959598958,
                22.117973773073757
              ],
              [
                89.52398952398954,
                21.814204794304786
              ],
              [
                89.55998955998956,
                21.715262898362894
              ],
              [
                89.59598959598958,
                21.715262898362894
              ],
              [
                89.59598959598958,
                21.76386593496592
              ],
              [
                89.66798966798967,
                21.74997935307934
              ],
              [
                89.70398970398969,
                21.78122416232415
              ],
              [
                89.63198963198965,
                21.871486944586934
              ],
              [
                89.63198963198965,
                21.9218258039258
              ],
              [
                89.66798966798967,
                21.85586453996453
              ],
              [
                89.70398970398969,
                21.82982719892719
              ],
              [
                89.77598977598979,
                21.82982719892719
              ],
              [
                89.8839898839899,
                21.88710934920934
              ],
              [
                89.84798984798982,
                22.03465428175427
              ],
              [
                89.8119898119898,
                22.076314027414014
              ],
              [
                89.8839898839899,
                22.09193643203642
              ],
              [
                89.84798984798982,
                22.26378288288288
              ],
              [
                89.8839898839899,
                22.338423260523243
              ],
              [
                89.8839898839899,
                22.42000692910692
              ],
              [
                89.91998991998992,
                22.395705410805405
              ],
              [
                89.99198999199001,
                22.46860996570996
              ],
              [
                89.95598995598993,
                22.51894882504881
              ],
              [
                89.95598995598993,
                22.583174266274256
              ],
              [
                89.95598995598993,
                22.591853379953363
              ],
              [
                89.91998991998992,
                22.66649375759374
              ],
              [
                89.91998991998992,
                22.682116162216147
              ],
              [
                89.8839898839899,
                22.706417680517674
              ],
              [
                89.95598995598993,
                22.82966109476108
              ],
              [
                89.90522990522993,
                22.878611295911284
              ],
              [
                89.66798966798967,
                23.107392732492727
              ],
              [
                89.66798966798967,
                23.13169425079424
              ],
              [
                89.70398970398969,
                23.123015137115132
              ],
              [
                89.77598977598979,
                23.173353996453983
              ],
              [
                89.70398970398969,
                23.173353996453983
              ],
              [
                89.66798966798967,
                23.221957033057024
              ],
              [
                89.63198963198965,
                23.23757943767943
              ],
              [
                89.66798966798967,
                23.28618247428247
              ],
              [
                89.63198963198965,
                23.28618247428247
              ],
              [
                89.59598959598958,
                23.352143738243726
              ],
              [
                89.59598959598958,
                23.386860192960185
              ],
              [
                89.63198963198965,
                23.369501965601955
              ],
              [
                89.59598959598958,
                23.475387152487144
              ],
              [
                89.52398952398954,
                23.50836778446778
              ],
              [
                89.48798948798947,
                23.484066266166252
              ],
              [
                89.52398952398954,
                23.5413484164484
              ],
              [
                89.41598941598943,
                23.671535121635117
              ],
              [
                89.34398934398934,
                23.671535121635117
              ],
              [
                89.30798930798932,
                23.720138158238143
              ],
              [
                89.34398934398934,
                23.85206068616067
              ],
              [
                89.34398934398934,
                23.91802195012194
              ],
              [
                89.12798912798911,
                23.951002582102575
              ],
              [
                88.98398898398898,
                24.16277295587294
              ],
              [
                88.83998883998885,
                24.12284903294902
              ],
              [
                88.73198873198874,
                24.18881029691029
              ],
              [
                88.69598869598872,
                24.147150551250533
              ],
              [
                88.69598869598872,
                24.098547514647507
              ],
              [
                88.69598869598872,
                24.081189287289277
              ],
              [
                88.73198873198874,
                24.04126536436536
              ],
              [
                88.73198873198874,
                24.032586250686236
              ],
              [
                88.73198873198874,
                23.990926505026493
              ],
              [
                88.73198873198874,
                23.975304100404088
              ],
              [
                88.73198873198874,
                23.926701063801048
              ],
              [
                88.65998865998864,
                23.87809802719802
              ],
              [
                88.5879885879886,
                23.86073979983979
              ],
              [
                88.57358857358855,
                23.772560004859997
              ],
              [
                88.55198855198853,
                23.640290312390306
              ],
              [
                88.73198873198874,
                23.466708038808022
              ],
              [
                88.76798876798875,
                23.484066266166252
              ],
              [
                88.69598869598872,
                23.294861587961577
              ],
              [
                88.69598869598872,
                23.25493766503766
              ],
              [
                88.98398898398898,
                23.206334628434618
              ],
              [
                88.83998883998885,
                23.07441210051209
              ],
              [
                88.83998883998885,
                22.9754702045702
              ],
              [
                88.94798894798896,
                22.853962613062606
              ],
              [
                88.91198891198894,
                22.737662489762485
              ],
              [
                88.94798894798896,
                22.591853379953363
              ],
              [
                88.91198891198894,
                22.543250343350337
              ],
              [
                88.96310896310894,
                22.53092600192599
              ],
              [
                88.98398898398898,
                22.525892115992107
              ],
              [
                89.019989019989,
                22.452987561087554
              ],
              [
                89.019989019989,
                22.426950220050216
              ],
              [
                89.019989019989,
                22.298499337599324
              ],
              [
                89.019989019989,
                22.289820223920216
              ],
              [
                89.05598905598907,
                22.175255923355905
              ]
            ],
            [
              [
                89.59598959598958,
                22.255103769203757
              ],
              [
                89.55998955998956,
                22.19782161892161
              ],
              [
                89.59598959598958,
                22.117973773073757
              ],
              [
                89.52398952398954,
                22.206500732600716
              ],
              [
                89.63198963198965,
                22.329744146844135
              ],
              [
                89.59598959598958,
                22.255103769203757
              ]
            ],
            [
              [
                89.52398952398954,
                22.09193643203642
              ],
              [
                89.52398952398954,
                22.076314027414014
              ],
              [
                89.48798948798947,
                22.133596177696162
              ],
              [
                89.48798948798947,
                22.27749588249587
              ],
              [
                89.48798948798947,
                22.298499337599324
              ],
              [
                89.52398952398954,
                22.09193643203642
              ]
            ]
          ],
          [
            [
              [
                89.05598905598907,
                21.78990327600326
              ],
              [
                89.12798912798911,
                21.715262898362894
              ],
              [
                89.12798912798911,
                21.76386593496592
              ],
              [
                89.09198909198909,
                21.78990327600326
              ],
              [
                89.05598905598907,
                21.9218258039258
              ],
              [
                89.05598905598907,
                21.78990327600326
              ]
            ]
          ]
        ]
      }
    },
    {
      "id": 251,
      "type": "Feature",
      "properties": {
        "id": "BGD-2475",
        "name": "Barisal",
        "cntr_code": "BD",
        "__source": "detail"
      },
      "geometry": {
        "type": "MultiPolygon",
        "coordinates": [
          [
            [
              [
                90.6759906759907,
                22.378347183447175
              ],
              [
                90.62919062919065,
                22.161369341469324
              ],
              [
                90.4959904959905,
                22.10061554571554
              ],
              [
                90.4959904959905,
                22.03465428175427
              ],
              [
                90.53199053199052,
                22.067634913734906
              ],
              [
                90.4959904959905,
                22.027710990810974
              ],
              [
                90.53199053199052,
                21.994730358830353
              ],
              [
                90.56799056799059,
                22.027710990810974
              ],
              [
                90.62199062199062,
                22.133596177696162
              ],
              [
                90.60399060399061,
                22.04333339543338
              ],
              [
                90.63999063999063,
                22.027710990810974
              ],
              [
                90.6759906759907,
                22.10061554571554
              ],
              [
                90.63999063999063,
                21.994730358830353
              ],
              [
                90.78399078399076,
                22.076314027414014
              ],
              [
                90.81999081999084,
                22.149218582318568
              ],
              [
                90.85599085599085,
                22.435629333729324
              ],
              [
                90.78399078399076,
                22.51894882504881
              ],
              [
                90.63999063999063,
                22.78973717183716
              ],
              [
                90.56799056799059,
                22.77237894447893
              ],
              [
                90.56799056799059,
                22.600532493632485
              ],
              [
                90.63999063999063,
                22.543250343350337
              ],
              [
                90.6759906759907,
                22.378347183447175
              ]
            ]
          ],
          [
            [
              [
                90.53199053199052,
                22.715096794196782
              ],
              [
                90.53199053199052,
                22.78973717183716
              ],
              [
                90.56799056799059,
                22.812302867402863
              ],
              [
                90.6759906759907,
                22.80362375372374
              ],
              [
                90.60399060399061,
                22.87826413136412
              ],
              [
                90.4959904959905,
                22.86958501768501
              ],
              [
                90.45999045999048,
                22.77237894447893
              ],
              [
                90.53199053199052,
                22.715096794196782
              ]
            ]
          ],
          [
            [
              [
                90.56799056799059,
                23.034488177588173
              ],
              [
                90.4959904959905,
                22.9754702045702
              ],
              [
                90.6759906759907,
                22.918188054288038
              ],
              [
                90.63999063999063,
                22.952904509004497
              ],
              [
                90.6759906759907,
                22.959847799947795
              ],
              [
                90.56799056799059,
                23.034488177588173
              ]
            ]
          ],
          [
            [
              [
                89.99198999199001,
                22.46860996570996
              ],
              [
                90.02799002799003,
                22.492911484011472
              ],
              [
                89.8839898839899,
                22.272461996561987
              ],
              [
                89.91998991998992,
                21.994730358830353
              ],
              [
                89.99198999199001,
                21.98605124515123
              ],
              [
                89.99198999199001,
                21.994730358830353
              ],
              [
                90.06039006039003,
                21.98605124515123
              ],
              [
                90.02799002799003,
                21.944391499491488
              ],
              [
                90.02799002799003,
                21.864543653643636
              ],
              [
                90.06399006399005,
                21.85586453996453
              ],
              [
                90.13599013599014,
                21.928769094869082
              ],
              [
                90.09999009999012,
                21.82982719892719
              ],
              [
                90.17199017199016,
                21.807261503361488
              ],
              [
                90.27999027999027,
                21.871486944586934
              ],
              [
                90.31599031599029,
                21.98605124515123
              ],
              [
                90.38799038799038,
                22.10929465939465
              ],
              [
                90.38799038799038,
                22.10061554571554
              ],
              [
                90.4239904239904,
                22.076314027414014
              ],
              [
                90.4959904959905,
                22.182199214299203
              ],
              [
                90.56799056799059,
                22.19782161892161
              ],
              [
                90.63999063999063,
                22.321065033165027
              ],
              [
                90.56799056799059,
                22.46860996570996
              ],
              [
                90.60399060399061,
                22.46166667476666
              ],
              [
                90.56799056799059,
                22.558872747972742
              ],
              [
                90.4959904959905,
                22.576230975330958
              ],
              [
                90.4239904239904,
                22.492911484011472
              ],
              [
                90.45999045999048,
                22.583174266274256
              ],
              [
                90.53199053199052,
                22.60747578457577
              ],
              [
                90.4959904959905,
                22.72377590787589
              ],
              [
                90.38799038799038,
                22.763699830799823
              ],
              [
                90.4239904239904,
                22.77237894447893
              ],
              [
                90.38799038799038,
                22.794944640044633
              ],
              [
                90.4959904959905,
                22.87826413136412
              ],
              [
                90.53199053199052,
                22.89562235872235
              ],
              [
                90.45999045999048,
                23.02580906390905
              ],
              [
                90.35199035199037,
                23.06573298683297
              ],
              [
                90.27999027999027,
                23.041431468531457
              ],
              [
                90.31599031599029,
                23.017129950229943
              ],
              [
                90.27999027999027,
                22.9754702045702
              ],
              [
                90.20799020799024,
                23.06573298683297
              ],
              [
                90.13599013599014,
                23.06573298683297
              ],
              [
                89.99198999199001,
                22.886943245043227
              ],
              [
                89.91998991998992,
                22.86958501768501
              ],
              [
                89.95598995598993,
                22.82966109476108
              ],
              [
                89.8839898839899,
                22.706417680517674
              ],
              [
                89.91998991998992,
                22.682116162216147
              ],
              [
                89.91998991998992,
                22.66649375759374
              ],
              [
                89.95598995598993,
                22.583174266274256
              ],
              [
                89.95598995598993,
                22.51894882504881
              ],
              [
                89.95598995598993,
                22.510269711369702
              ],
              [
                89.99198999199001,
                22.46860996570996
              ]
            ],
            [
              [
                90.06399006399005,
                22.166576809676798
              ],
              [
                89.99198999199001,
                21.994730358830353
              ],
              [
                89.99198999199001,
                22.0520125091125
              ],
              [
                90.06399006399005,
                22.166576809676798
              ]
            ],
            [
              [
                90.4239904239904,
                22.19087832797831
              ],
              [
                90.38799038799038,
                22.289820223920216
              ],
              [
                90.4239904239904,
                22.19782161892161
              ],
              [
                90.4239904239904,
                22.19087832797831
              ]
            ],
            [
              [
                90.20799020799024,
                22.124917064017055
              ],
              [
                90.17199017199016,
                22.117973773073757
              ],
              [
                90.06759006759006,
                21.99299453609453
              ],
              [
                90.13599013599014,
                22.117973773073757
              ],
              [
                90.20799020799024,
                22.133596177696162
              ],
              [
                90.24399024399025,
                22.19782161892161
              ],
              [
                90.20799020799024,
                22.124917064017055
              ]
            ]
          ],
          [
            [
              [
                90.60399060399061,
                21.98605124515123
              ],
              [
                90.53199053199052,
                21.93571238581238
              ],
              [
                90.53199053199052,
                21.87843023553023
              ],
              [
                90.4959904959905,
                21.864543653643636
              ],
              [
                90.53199053199052,
                21.871486944586934
              ],
              [
                90.60399060399061,
                21.93571238581238
              ],
              [
                90.60399060399061,
                21.98605124515123
              ]
            ]
          ],
          [
            [
              [
                90.4959904959905,
                22.001673649773636
              ],
              [
                90.4239904239904,
                22.04333339543338
              ],
              [
                90.38799038799038,
                21.913146690246677
              ],
              [
                90.4959904959905,
                21.944391499491488
              ],
              [
                90.4959904959905,
                22.001673649773636
              ]
            ]
          ]
        ]
      }
    },
    {
      "id": 252,
      "type": "Feature",
      "properties": {
        "id": "BGD-2476",
        "name": "Chittagong",
        "cntr_code": "BD",
        "__source": "detail"
      },
      "geometry": {
        "type": "MultiPolygon",
        "coordinates": [
          [
            [
              [
                91.79199179199179,
                22.303706805806797
              ],
              [
                91.86399186399188,
                22.248160478260473
              ],
              [
                91.79199179199179,
                22.182199214299203
              ],
              [
                91.86399186399188,
                22.117973773073757
              ],
              [
                91.86399186399188,
                22.133596177696162
              ],
              [
                91.8999918999919,
                21.864543653643636
              ],
              [
                91.93599193599192,
                21.88710934920934
              ],
              [
                91.8999918999919,
                21.78990327600326
              ],
              [
                92.00799200799202,
                21.78990327600326
              ],
              [
                91.93599193599192,
                21.715262898362894
              ],
              [
                91.971991971992,
                21.69269720279719
              ],
              [
                92.00799200799202,
                21.706583784683772
              ],
              [
                92.00799200799202,
                21.65103745713745
              ],
              [
                92.04399204399203,
                21.706583784683772
              ],
              [
                92.04399204399203,
                21.642358343458326
              ],
              [
                92.00799200799202,
                21.560774674874665
              ],
              [
                92.00799200799202,
                21.494813410913395
              ],
              [
                91.93599193599192,
                21.444474551574544
              ],
              [
                92.04399204399203,
                21.298665441765436
              ],
              [
                92.04399204399203,
                21.159799622899612
              ],
              [
                92.18799218799217,
                20.996632285732275
              ],
              [
                92.33199233199235,
                20.74146634356633
              ],
              [
                92.33199233199235,
                20.774446975546965
              ],
              [
                92.25999225999226,
                20.939350135450127
              ],
              [
                92.25999225999226,
                21.06085772695772
              ],
              [
                92.18799218799217,
                21.175422027522018
              ],
              [
                92.18799218799217,
                21.298665441765436
              ],
              [
                92.22399222399224,
                21.42190885600884
              ],
              [
                92.36799236799237,
                21.444474551574544
              ],
              [
                92.36799236799237,
                21.417569299169287
              ],
              [
                92.36799236799237,
                21.380249110349098
              ],
              [
                92.5119925119925,
                21.364626705726693
              ],
              [
                92.54799254799258,
                21.241383291483274
              ],
              [
                92.65599265599263,
                21.298665441765436
              ],
              [
                92.5839925839926,
                21.47051189261188
              ],
              [
                92.5839925839926,
                21.494813410913395
              ],
              [
                92.5839925839926,
                21.88710934920934
              ],
              [
                92.54799254799258,
                22.124917064017055
              ],
              [
                92.5839925839926,
                22.175255923355905
              ],
              [
                92.54799254799258,
                22.43649724509723
              ],
              [
                92.5119925119925,
                22.697738566838552
              ],
              [
                92.43999243999247,
                22.763699830799823
              ],
              [
                92.40399240399239,
                22.86958501768501
              ],
              [
                92.36799236799237,
                22.92686716796716
              ],
              [
                92.33199233199235,
                23.173353996453983
              ],
              [
                92.33199233199235,
                23.352143738243726
              ],
              [
                92.25999225999226,
                23.60730968040967
              ],
              [
                92.25999225999226,
                23.706251576351562
              ],
              [
                92.24775224775226,
                23.706251576351562
              ],
              [
                92.22399222399224,
                23.706251576351562
              ],
              [
                92.18799218799217,
                23.648969426069414
              ],
              [
                92.15199215199215,
                23.737496385596373
              ],
              [
                92.00799200799202,
                23.640290312390306
              ],
              [
                91.93599193599192,
                23.720138158238143
              ],
              [
                91.93599193599192,
                23.671535121635117
              ],
              [
                91.93599193599192,
                23.492745379845374
              ],
              [
                91.79199179199179,
                23.40248259758259
              ],
              [
                91.75599175599177,
                23.272295892395874
              ],
              [
                91.79199179199179,
                23.09177032787032
              ],
              [
                91.76499176499175,
                23.057921784521767
              ],
              [
                91.7199917199917,
                23.001507545607538
              ],
              [
                91.57599157599157,
                22.94422539532539
              ],
              [
                91.53999153999155,
                23.001507545607538
              ],
              [
                91.46799146799145,
                23.18897640107639
              ],
              [
                91.39599139599142,
                23.263616778716766
              ],
              [
                91.35999135999134,
                23.221957033057024
              ],
              [
                91.39599139599142,
                23.06573298683297
              ],
              [
                91.32399132399132,
                23.098713618813605
              ],
              [
                91.25199125199123,
                23.329578042678037
              ],
              [
                91.2879912879913,
                23.352143738243726
              ],
              [
                91.14399114399117,
                23.631611198711184
              ],
              [
                91.17999117999119,
                23.671535121635117
              ],
              [
                91.14399114399117,
                23.720138158238143
              ],
              [
                91.17099117099116,
                23.746175499275495
              ],
              [
                91.17999117999119,
                23.754854612954603
              ],
              [
                91.21599121599121,
                23.827759167859156
              ],
              [
                91.21599121599121,
                23.909342836442832
              ],
              [
                91.25199125199123,
                23.975304100404088
              ],
              [
                91.32399132399132,
                23.990926505026493
              ],
              [
                91.2879912879913,
                24.147150551250533
              ],
              [
                91.32399132399132,
                24.18013118323117
              ],
              [
                91.2879912879913,
                24.204432701532696
              ],
              [
                91.32399132399132,
                24.237413333513317
              ],
              [
                91.25199125199123,
                24.21137599247598
              ],
              [
                91.14399114399117,
                24.254771560871546
              ],
              [
                91.1079911079911,
                24.237413333513317
              ],
              [
                91.1079911079911,
                24.231685118485103
              ],
              [
                91.1079911079911,
                24.21137599247598
              ],
              [
                91.07595107595108,
                24.21137599247598
              ],
              [
                91.07199107199108,
                24.21137599247598
              ],
              [
                90.99999099999098,
                24.16277295587294
              ],
              [
                91.03599103599106,
                24.089868400968385
              ],
              [
                90.89199089199087,
                23.87809802719802
              ],
              [
                90.78399078399076,
                23.85206068616067
              ],
              [
                90.71199071199072,
                23.720138158238143
              ],
              [
                90.78399078399076,
                23.622932085032076
              ],
              [
                90.71199071199072,
                23.550027530127522
              ],
              [
                90.71199071199072,
                23.50836778446778
              ],
              [
                90.71199071199072,
                23.499688670788657
              ],
              [
                90.63999063999063,
                23.484066266166252
              ],
              [
                90.60399060399061,
                23.451085634185617
              ],
              [
                90.60399060399061,
                23.338257156357145
              ],
              [
                90.6759906759907,
                23.329578042678037
              ],
              [
                90.6759906759907,
                23.272295892395874
              ],
              [
                90.63999063999063,
                23.06573298683297
              ],
              [
                90.71199071199072,
                22.935546281646268
              ],
              [
                90.78399078399076,
                22.781058058158052
              ],
              [
                90.96399096399097,
                22.576230975330958
              ],
              [
                91.03599103599106,
                22.591853379953363
              ],
              [
                90.99999099999098,
                22.682116162216147
              ],
              [
                91.07199107199108,
                22.576230975330958
              ],
              [
                91.14399114399117,
                22.525892115992107
              ],
              [
                91.21599121599121,
                22.558872747972742
              ],
              [
                91.25199125199123,
                22.624834011934
              ],
              [
                91.25199125199123,
                22.66649375759374
              ],
              [
                91.17999117999119,
                22.682116162216147
              ],
              [
                91.17999117999119,
                22.730719198819187
              ],
              [
                91.32399132399132,
                22.697738566838552
              ],
              [
                91.32399132399132,
                22.72377590787589
              ],
              [
                91.2879912879913,
                22.737662489762485
              ],
              [
                91.35999135999134,
                22.737662489762485
              ],
              [
                91.32399132399132,
                22.781058058158052
              ],
              [
                91.43199143199143,
                22.7550207171207
              ],
              [
                91.46799146799145,
                22.902565649665632
              ],
              [
                91.46799146799145,
                22.763699830799823
              ],
              [
                91.53999153999155,
                22.697738566838552
              ],
              [
                91.68399168399168,
                22.534571229671215
              ],
              [
                91.75599175599177,
                22.41306363816362
              ],
              [
                91.79199179199179,
                22.23948136458135
              ],
              [
                91.82799182799181,
                22.248160478260473
              ],
              [
                91.79199179199179,
                22.303706805806797
              ]
            ],
            [
              [
                91.79199179199179,
                22.303706805806797
              ],
              [
                91.86399186399188,
                22.36272477882477
              ],
              [
                91.8999918999919,
                22.426950220050216
              ],
              [
                91.86399186399188,
                22.329744146844135
              ],
              [
                91.79199179199179,
                22.303706805806797
              ]
            ]
          ],
          [
            [
              [
                91.86399186399188,
                21.47919100629099
              ],
              [
                91.971991971992,
                21.519114929214922
              ],
              [
                92.00799200799202,
                21.609377711477705
              ],
              [
                91.93599193599192,
                21.715262898362894
              ],
              [
                91.93599193599192,
                21.78122416232415
              ],
              [
                91.8999918999919,
                21.772545048645043
              ],
              [
                91.8999918999919,
                21.741300239400232
              ],
              [
                91.87119187119185,
                21.75345099855099
              ],
              [
                91.8999918999919,
                21.85586453996453
              ],
              [
                91.86399186399188,
                21.928769094869082
              ],
              [
                91.82799182799181,
                21.87843023553023
              ],
              [
                91.82799182799181,
                21.723942012042002
              ],
              [
                91.86399186399188,
                21.73262112572111
              ],
              [
                91.86399186399188,
                21.47919100629099
              ]
            ]
          ],
          [
            [
              [
                91.57599157599157,
                22.395705410805405
              ],
              [
                91.57599157599157,
                22.477289079389067
              ],
              [
                91.46799146799145,
                22.591853379953363
              ],
              [
                91.43199143199143,
                22.576230975330958
              ],
              [
                91.43199143199143,
                22.525892115992107
              ],
              [
                91.46799146799145,
                22.41306363816362
              ],
              [
                91.57599157599157,
                22.395705410805405
              ]
            ]
          ],
          [
            [
              [
                91.07199107199108,
                22.10061554571554
              ],
              [
                91.17999117999119,
                22.19087832797831
              ],
              [
                91.14399114399117,
                22.329744146844135
              ],
              [
                91.07199107199108,
                22.395705410805405
              ],
              [
                91.03599103599106,
                22.19087832797831
              ],
              [
                90.99999099999098,
                22.117973773073757
              ],
              [
                91.03599103599106,
                22.09193643203642
              ],
              [
                91.07199107199108,
                22.10061554571554
              ]
            ]
          ]
        ]
      }
    },
    {
      "id": 253,
      "type": "Feature",
      "properties": {
        "id": "BGD-2488",
        "name": "Sylhet",
        "cntr_code": "BD",
        "__source": "detail"
      },
      "geometry": {
        "type": "Polygon",
        "coordinates": [
          [
            [
              92.07999207999211,
              24.38322244332244
            ],
            [
              92.11599211599213,
              24.515144971244965
            ],
            [
              92.22399222399224,
              24.777254204354193
            ],
            [
              92.22399222399224,
              24.843215468315464
            ],
            [
              92.22399222399224,
              24.89181850491849
            ],
            [
              92.29599229599228,
              24.89181850491849
            ],
            [
              92.36799236799237,
              24.83453635463634
            ],
            [
              92.47599247599248,
              24.883139391239382
            ],
            [
              92.47599247599248,
              24.924799136899125
            ],
            [
              92.29599229599228,
              25.072344069444057
            ],
            [
              92.04399204399203,
              25.178229256329246
            ],
            [
              91.94679194679196,
              25.173542534942527
            ],
            [
              91.75599175599177,
              25.164342674442665
            ],
            [
              91.7199917199917,
              25.16260685170684
            ],
            [
              91.64799164799166,
              25.120947106047097
            ],
            [
              91.57599157599157,
              25.16260685170684
            ],
            [
              91.54719154719157,
              25.157399383499367
            ],
            [
              91.43199143199143,
              25.136569510669503
            ],
            [
              91.2879912879913,
              25.189338521838508
            ],
            [
              91.25199125199123,
              25.20253077463076
            ],
            [
              90.92799092799095,
              25.16260685170684
            ],
            [
              90.96399096399097,
              25.054985842085827
            ],
            [
              90.89199089199087,
              24.973402173502166
            ],
            [
              90.96399096399097,
              24.883139391239382
            ],
            [
              91.14399114399117,
              24.883139391239382
            ],
            [
              91.14399114399117,
              24.695670535770518
            ],
            [
              91.21599121599121,
              24.680048131148126
            ],
            [
              91.17999117999119,
              24.614086867186856
            ],
            [
              91.25199125199123,
              24.556804716904708
            ],
            [
              91.17999117999119,
              24.48216433926433
            ],
            [
              91.25199125199123,
              24.466541934641924
            ],
            [
              91.21599121599121,
              24.417938898038884
            ],
            [
              91.25199125199123,
              24.37627915237914
            ],
            [
              91.14399114399117,
              24.254771560871546
            ],
            [
              91.25199125199123,
              24.21137599247598
            ],
            [
              91.32399132399132,
              24.237413333513317
            ],
            [
              91.2879912879913,
              24.204432701532696
            ],
            [
              91.32399132399132,
              24.18013118323117
            ],
            [
              91.2879912879913,
              24.147150551250533
            ],
            [
              91.32399132399132,
              23.990926505026493
            ],
            [
              91.32399132399132,
              23.991447251847234
            ],
            [
              91.32399132399132,
              23.9996056187056
            ],
            [
              91.35999135999134,
              24.098547514647507
            ],
            [
              91.61199161199164,
              24.10549080559079
            ],
            [
              91.61199161199164,
              24.21137599247598
            ],
            [
              91.64799164799166,
              24.179263271863263
            ],
            [
              91.68399168399168,
              24.147150551250533
            ],
            [
              91.7199917199917,
              24.16277295587294
            ],
            [
              91.7199917199917,
              24.22873421983421
            ],
            [
              91.75599175599177,
              24.224394662994655
            ],
            [
              91.7775917775918,
              24.22179092889091
            ],
            [
              91.79199179199179,
              24.2200551061551
            ],
            [
              91.86399186399188,
              24.15409384219383
            ],
            [
              91.8999918999919,
              24.343298520398506
            ],
            [
              91.93599193599192,
              24.33114776124775
            ],
            [
              91.971991971992,
              24.318997002096992
            ],
            [
              91.93599193599192,
              24.37627915237914
            ],
            [
              92.07999207999211,
              24.38322244332244
            ]
          ]
        ]
      }
    },
    {
      "id": 254,
      "type": "Feature",
      "properties": {
        "id": "BGD-3255",
        "name": "Rajshahi",
        "cntr_code": "BD",
        "__source": "detail"
      },
      "geometry": {
        "type": "Polygon",
        "coordinates": [
          [
            [
              88.73198873198874,
              24.18881029691029
            ],
            [
              88.83998883998885,
              24.12284903294902
            ],
            [
              88.91198891198894,
              24.17145206955206
            ],
            [
              88.98398898398898,
              24.16277295587294
            ],
            [
              89.05598905598907,
              24.048208655308642
            ],
            [
              89.05598905598907,
              23.9996056187056
            ],
            [
              89.16398916398919,
              23.93538017748017
            ],
            [
              89.23022923022921,
              23.93538017748017
            ],
            [
              89.30798930798932,
              23.93538017748017
            ],
            [
              89.55998955998956,
              23.81213676323675
            ],
            [
              89.70398970398969,
              23.85206068616067
            ],
            [
              89.70398970398969,
              23.983983214083196
            ],
            [
              89.8119898119898,
              24.056887768987764
            ],
            [
              89.8119898119898,
              24.081189287289277
            ],
            [
              89.8119898119898,
              24.16277295587294
            ],
            [
              89.77598977598979,
              24.27733725643725
            ],
            [
              89.8119898119898,
              24.719972054072045
            ],
            [
              89.66798966798967,
              24.85189458199457
            ],
            [
              89.66798966798967,
              24.966458882558868
            ],
            [
              89.66798966798967,
              25.16260685170684
            ],
            [
              89.34398934398934,
              25.21120988830988
            ],
            [
              89.2719892719893,
              25.171285965385948
            ],
            [
              89.23598923598922,
              25.294529379629367
            ],
            [
              88.98398898398898,
              25.29973684783684
            ],
            [
              88.91198891198894,
              25.18517254727253
            ],
            [
              88.91198891198894,
              25.16260685170684
            ],
            [
              88.83998883998885,
              25.19385166095165
            ],
            [
              88.76798876798875,
              25.16260685170684
            ],
            [
              88.44398844398847,
              25.18517254727253
            ],
            [
              88.4079884079884,
              25.022005210105192
            ],
            [
              88.29998829998829,
              24.867516986616977
            ],
            [
              88.26398826398827,
              24.883139391239382
            ],
            [
              88.22798822798825,
              24.94910065520064
            ],
            [
              88.11998811998814,
              24.916120023220017
            ],
            [
              88.15598815598815,
              24.843215468315464
            ],
            [
              88.04798804798804,
              24.751216863316856
            ],
            [
              88.01198801198802,
              24.645331676431667
            ],
            [
              88.08398808398806,
              24.60540775350775
            ],
            [
              88.11998811998814,
              24.49952256662256
            ],
            [
              88.15598815598815,
              24.48147001017
            ],
            [
              88.47998847998849,
              24.318997002096992
            ],
            [
              88.62398862398862,
              24.29469548379548
            ],
            [
              88.69598869598872,
              24.334619406719398
            ],
            [
              88.73198873198874,
              24.286016370116357
            ],
            [
              88.73198873198874,
              24.204432701532696
            ],
            [
              88.73198873198874,
              24.18881029691029
            ]
          ]
        ]
      }
    },
    {
      "id": 255,
      "type": "Feature",
      "properties": {
        "id": "BGD-5492",
        "name": "Rangpur",
        "cntr_code": "BD",
        "__source": "detail"
      },
      "geometry": {
        "type": "Polygon",
        "coordinates": [
          [
            [
              89.7939897939898,
              25.39954665514665
            ],
            [
              89.8119898119898,
              25.41603697113696
            ],
            [
              89.8119898119898,
              25.636486458586447
            ],
            [
              89.77598977598979,
              25.817012023112014
            ],
            [
              89.8119898119898,
              25.93157632367631
            ],
            [
              89.77598977598979,
              25.947198728298716
            ],
            [
              89.8119898119898,
              25.97150024660023
            ],
            [
              89.77598977598979,
              26.0374615105615
            ],
            [
              89.73998973998977,
              26.145082520182513
            ],
            [
              89.66798966798967,
              26.160704924804918
            ],
            [
              89.66798966798967,
              26.22493036603035
            ],
            [
              89.63198963198965,
              26.217987075087066
            ],
            [
              89.63198963198965,
              26.18500644310643
            ],
            [
              89.63198963198965,
              26.176327329427323
            ],
            [
              89.63198963198965,
              26.1676482157482
            ],
            [
              89.59598959598958,
              26.15636536796535
            ],
            [
              89.55998955998956,
              26.145082520182513
            ],
            [
              89.59598959598958,
              26.11904517914516
            ],
            [
              89.55998955998956,
              26.087800369900364
            ],
            [
              89.63198963198965,
              26.070442142542134
            ],
            [
              89.52398952398954,
              25.964556955656946
            ],
            [
              89.48798948798947,
              25.99753758763758
            ],
            [
              89.45198945198945,
              25.99753758763758
            ],
            [
              89.34398934398934,
              25.99753758763758
            ],
            [
              89.12798912798911,
              26.145082520182513
            ],
            [
              89.05598905598907,
              26.29089162999162
            ],
            [
              89.12798912798911,
              26.32560808470808
            ],
            [
              89.09198909198909,
              26.35338124848124
            ],
            [
              89.05598905598907,
              26.381154412254403
            ],
            [
              88.94798894798896,
              26.438436562536552
            ],
            [
              88.91198891198894,
              26.40979548739547
            ],
            [
              88.87598887598887,
              26.381154412254403
            ],
            [
              88.98398898398898,
              26.29089162999162
            ],
            [
              89.019989019989,
              26.299570743670728
            ],
            [
              89.05598905598907,
              26.24228859338858
            ],
            [
              88.98398898398898,
              26.22493036603035
            ],
            [
              88.87598887598887,
              26.275269225369215
            ],
            [
              88.83998883998885,
              26.22493036603035
            ],
            [
              88.73198873198874,
              26.29089162999162
            ],
            [
              88.65998865998864,
              26.268325934425917
            ],
            [
              88.62398862398862,
              26.275269225369215
            ],
            [
              88.73198873198874,
              26.32560808470808
            ],
            [
              88.69598869598872,
              26.369871564471552
            ],
            [
              88.65998865998864,
              26.41413504423504
            ],
            [
              88.4079884079884,
              26.54432174942174
            ],
            [
              88.4079884079884,
              26.61896212706212
            ],
            [
              88.37198837198838,
              26.610283013382997
            ],
            [
              88.29998829998829,
              26.462738080838065
            ],
            [
              88.33598833598836,
              26.44711567621566
            ],
            [
              88.37198837198838,
              26.488775421875417
            ],
            [
              88.44398844398847,
              26.44711567621566
            ],
            [
              88.51598851598851,
              26.356852893952876
            ],
            [
              88.44398844398847,
              26.365532007631998
            ],
            [
              88.33598833598836,
              26.282212516312498
            ],
            [
              88.33598833598836,
              26.217987075087066
            ],
            [
              88.15598815598815,
              26.127724292824283
            ],
            [
              88.15598815598815,
              26.0374615105615
            ],
            [
              88.08398808398806,
              25.907274805374797
            ],
            [
              88.11998811998814,
              25.768408986508973
            ],
            [
              88.26398826398827,
              25.78403139113138
            ],
            [
              88.4079884079884,
              25.653844685944676
            ],
            [
              88.4079884079884,
              25.596562535662528
            ],
            [
              88.4079884079884,
              25.587883421983406
            ],
            [
              88.55198855198853,
              25.497620639720623
            ],
            [
              88.65998865998864,
              25.46464000774
            ],
            [
              88.73198873198874,
              25.513243044343028
            ],
            [
              88.83998883998885,
              25.457696716796704
            ],
            [
              88.80398880398883,
              25.400414566514556
            ],
            [
              88.83998883998885,
              25.325774188874178
            ],
            [
              89.23598923598922,
              25.294529379629367
            ],
            [
              89.2719892719893,
              25.171285965385948
            ],
            [
              89.34398934398934,
              25.21120988830988
            ],
            [
              89.66798966798967,
              25.16260685170684
            ],
            [
              89.73998973998977,
              25.24245469755469
            ],
            [
              89.77598977598979,
              25.383056339156326
            ],
            [
              89.7939897939898,
              25.39954665514665
            ]
          ]
        ]
      }
    }
  ]
}
