{
  "type": "FeatureCollection",
  "features": [
    {
      "id": 7593,
      "type": "Feature",
      "properties": {
        "id": "LU_ADM1_LUX-906",
        "name": "Diekirch",
        "cntr_code": "LU",
        "admin1_group": "Diekirch",
        "detail_tier": "adm1_basic",
        "__source": "detail"
      },
      "geometry": {
        "type": "Polygon",
        "coordinates": [
          [
            [
              6.096786096786104,
              50.14821289341289
            ],
            [
              6.006066006066021,
              50.170084259884234
            ],
            [
              6.003186003186016,
              50.170778588978564
            ],
            [
              5.887985887985877,
              50.10308150228148
            ],
            [
              5.779985779985793,
              49.94685745605743
            ],
            [
              5.743985743985746,
              49.858330496530485
            ],
            [
              5.859185859185857,
              49.70557809577808
            ],
            [
              5.992385992386005,
              49.72814379134378
            ],
            [
              6.042786042786048,
              49.823614041814025
            ],
            [
              6.247986247986262,
              49.790633409833404
            ],
            [
              6.294786294786292,
              49.84791556011554
            ],
            [
              6.121986121986112,
              49.997196315396295
            ],
            [
              6.096786096786104,
              50.14821289341289
            ]
          ]
        ]
      }
    },
    {
      "id": 7594,
      "type": "Feature",
      "properties": {
        "id": "LU_ADM1_LUX-907",
        "name": "Grevenmacher",
        "cntr_code": "LU",
        "admin1_group": "Grevenmacher",
        "detail_tier": "adm1_basic",
        "__source": "detail"
      },
      "geometry": {
        "type": "Polygon",
        "coordinates": [
          [
            [
              6.395586395586406,
              49.80972745992746
            ],
            [
              6.262386262386258,
              49.84097226917227
            ],
            [
              6.262386262386258,
              49.8083388017388
            ],
            [
              6.262386262386258,
              49.77570533430533
            ],
            [
              6.262386262386258,
              49.760950841050814
            ],
            [
              6.262386262386258,
              49.74723784143784
            ],
            [
              6.175986175986168,
              49.689955691155674
            ],
            [
              6.28398628398628,
              49.67433328653327
            ],
            [
              6.30198630198629,
              49.59274961794959
            ],
            [
              6.233586233586237,
              49.54067493587492
            ],
            [
              6.247986247986262,
              49.49901519021519
            ],
            [
              6.345186345186335,
              49.481656962856945
            ],
            [
              6.352386352386361,
              49.56671227691227
            ],
            [
              6.417186417186429,
              49.637881009081
            ],
            [
              6.402786402786404,
              49.655239236439215
            ],
            [
              6.496386496386492,
              49.715993032193026
            ],
            [
              6.499986499986505,
              49.755916955116945
            ],
            [
              6.503586503586519,
              49.79584087804086
            ],
            [
              6.496386496386492,
              49.79931252351251
            ],
            [
              6.463986463986458,
              49.80625581445581
            ],
            [
              6.395586395586406,
              49.80972745992746
            ]
          ]
        ]
      }
    },
    {
      "id": 7595,
      "type": "Feature",
      "properties": {
        "id": "LU_ADM1_LUX-908",
        "name": "Luxembourg",
        "cntr_code": "LU",
        "admin1_group": "Luxembourg",
        "detail_tier": "adm1_basic",
        "__source": "detail"
      },
      "geometry": {
        "type": "Polygon",
        "coordinates": [
          [
            [
              5.815985815985812,
              49.54588240408238
            ],
            [
              5.851985851985859,
              49.52782984762983
            ],
            [
              5.959985959985971,
              49.47367217827217
            ],
            [
              5.99598599598599,
              49.45561962181962
            ],
            [
              6.121986121986112,
              49.477317406017406
            ],
            [
              6.247986247986262,
              49.49901519021519
            ],
            [
              6.233586233586237,
              49.55456151776151
            ],
            [
              6.312786312786301,
              49.62746607266605
            ],
            [
              6.276786276786282,
              49.68127657747657
            ],
            [
              6.175986175986168,
              49.689955691155674
            ],
            [
              6.273186273186269,
              49.76980353700351
            ],
            [
              6.183186183186194,
              49.818406573606566
            ],
            [
              6.042786042786048,
              49.823614041814025
            ],
            [
              5.992385992386005,
              49.72814379134378
            ],
            [
              5.859185859185857,
              49.70557809577808
            ],
            [
              5.8843858843858925,
              49.64308847728846
            ],
            [
              5.815985815985812,
              49.54588240408238
            ]
          ]
        ]
      }
    }
  ]
}
